<CreaditDetails>
  <Details Name="sc_card_name">
  <Feature>uob-lady-s-platinum-card</Feature></Details>

  <Details Name="sc_cashback_percent">
  </Details>

  <Details Name="sc_airmile_per_sgd">
  </Details>
  
  <Details Name="sc_main_benefit">
  </Details>
  
  <Details Name="sc_main_benefit_rating">
  </Details>

  <Details Name="sc_promotion_details">
  </Details>
  
  <Details Name="sc_promotion_cond">
  </Details>
  
  <Details Name="sc_promotion_end">
  </Details>

  <Details Name="sc_gift_details">
  </Details>
  
  <Details Name="sc_gift_cond">
  </Details>
  
  <Details Name="sc_gift_end">
  </Details>

  <Details Name="sc_annual_fee">
  <Feature>192.60</Feature></Details>
  
  <Details Name="sc_sup_annual_fee">
  <Feature>96.30</Feature></Details>
  
  <Details Name="sc_fc_trans_fee">
  </Details>
  
  <Details Name="sc_other_fee">
  <Feature>Fee Waiver</Feature><Feature>Annual Interest Rate/ APR</Feature></Details>

  <Details Name="sc_local_income">
  <Feature>30000</Feature></Details>
  
  <Details Name="sc_foreigner_income">
  <Feature>40000</Feature></Details>

  <Details Name="sc_main_card_age">
  </Details>
  
  <Details Name="sc_sup_card_age">
  </Details>

  <Details Name="sc_disclosure">
  </Details>

  <Details Name="sc_airmiles_details">
  </Details>
  
  <Details Name="sc_airmiles_rating">
  </Details>

  <Details Name="sc_cashback_details">
  </Details>
  
  <Details Name="sc_cashback_rating">
  </Details>

  <Details Name="sc_dining_details">
  </Details>
  
  <Details Name="sc_dining_rating">
  </Details>

  <Details Name="sc_entertainment_details">
  <Feature>S$5 = 1 UNI$</Feature><Feature>5X UNI$ on overseas and online spend</Feature></Details>
  
  <Details Name="sc_entertainment_rating">
  <Feature>2</Feature></Details>

  <Details Name="sc_grocery_details">
  </Details>
  
  <Details Name="sc_grocery_rating">
  </Details>

  <Details Name="sc_petrol_details">
  </Details>
  
  <Details Name="sc_petrol_rating">    
  </Details>

  <Details Name="sc_rewards_details">
  <Feature>S$5 = 1 UNI$</Feature><Feature>5X UNI$ at local departmental stores, overseas and online shops</Feature><Feature>Min. spend of S$3,000 in a statement cycle, cap at UNI$4,000</Feature></Details>
  
  <Details Name="sc_rewards_rating">   
  <Feature>3</Feature></Details>

  <Details Name="sc_shopping_details">
  <Feature>S$5 = 1 UNI$</Feature><Feature>5X UNI$ at local departmental stores, overseas and online shops</Feature><Feature>UOB Lady&#226;&#8364;&#8482;s LuxePay Plan &#226;&#8364;&#8220; 6 or 12 month installment plan with no interest or processing fees</Feature></Details>
  
  <Details Name="sc_shopping_rating">
  <Feature>4</Feature></Details>

  <Details Name="sc_student_details">
  </Details>
  
  <Details Name="sc_student_rating">
  </Details>

  <Details Name="sc_main_image">
  <Feature>./images/uob-lady-s-platinum-card.png</Feature></Details>

</CreaditDetails>