<CreaditDetails>
  <Details Name="sc_card_name">
  <Feature>UOB Prvi Miles Platinum American Express Card</Feature></Details>

  <Details Name="sc_cashback_percent">
  </Details>

  <Details Name="sc_airmile_per_sgd">
  </Details>
  
  <Details Name="sc_main_benefit">
  <Feature>Complimentary 1-way limousine transfer to Changi Airport and travel insurance. Bonus 20,000 miles and waiver on annual fee with minimum S$50,000 annual spend.</Feature><Feature>Fastest earn rate - 3 miles for every S$1 spent on Singapore Airlines, SilkAir and KrisShop, 2.4 miles for every S$1 spent overseas and 1.4 miles for every S$1 spent locally, with no minimum spend. Plus, choice to redeem from over 40 airlines, cash or travel packages.</Feature><Feature>Receive a Samsonite Engenero Spinner 69cm Luggage worth S$560 when you apply now!</Feature></Details>
  
  <Details Name="sc_main_benefit_rating">
  </Details>

  <Details Name="sc_promotion_details">
  </Details>
  
  <Details Name="sc_promotion_cond">
  </Details>
  
  <Details Name="sc_promotion_end">
  <Feature>29-Feb-2016</Feature></Details>

  <Details Name="sc_gift_details">
  <Feature>1. 8,000 air miles for New UOB card applicants  OR</Feature><Feature>2. 5,000 air miles for existing UOB cardholders applying for PRVI Miles Credit Cards</Feature></Details>
  
  <Details Name="sc_gift_cond">
  <Feature>1. Promotion limited to first 1,000 successful applicants who spend a min. of S$1,500 within the first month.</Feature><Feature>2. Qualified Applicants who have never been issued any UOB credit cards shall be entitled to 8,000 air miles.</Feature><Feature>3. Qualified Applicants who have active UOB cards issued to them shall be entitled to 5,000 air miles.</Feature></Details>
  
  <Details Name="sc_gift_end">
  <Feature>29-Feb-2016</Feature></Details>

  <Details Name="sc_annual_fee">
  <Feature>256.80</Feature></Details>
  
  <Details Name="sc_sup_annual_fee">
  <Feature>128.40</Feature></Details>
  
  <Details Name="sc_fc_trans_fee">
  <Feature>3.25%</Feature></Details>
  
  <Details Name="sc_other_fee">
  <Feature>Fee Waiver</Feature><Feature>Annual Interest Rate/ APR</Feature></Details>

  <Details Name="sc_local_income">
  <Feature>80000</Feature></Details>
  
  <Details Name="sc_foreigner_income">
  <Feature>80000</Feature></Details>

  <Details Name="sc_main_card_age">
  <Feature>21</Feature></Details>
  
  <Details Name="sc_sup_card_age">
  <Feature>18</Feature></Details>

  <Details Name="sc_disclosure">
  <Feature>Complimentary limousine is applicable to UOB PRVI Miles American Express Cardmembers only. Please make the limousine booking at least 2 days prior to travel date.</Feature><Feature>Samsonite Engenero Spinner 69cm Luggage applicable to cards approved from 1 October - 31 December 2015 and not applicable to existing UOB PRVI Miles Cardmembers. Promotion is limited to first 300 successful card applicants in each qualifying period, who make a minimum spend of S$3,000 within a month from card approval date.</Feature><Feature>Cardmembers will earn UNI$7.5 for every S$5 spent at Singapore Airlines, SilkAir and KrisShop (equivalent to 3 miles for every S$1 spent), UNI$6 for every S$5 spent on transactions in foreign currencies (equivalent to 2.4 miles for every S$1 spent) and UNI$3.5 for every S$5 spent on transactions in Singapore Dollars (equivalent to 1.4 miles for every S$1 spent).</Feature></Details>

  <Details Name="sc_airmiles_details">
  <Feature>$1 = 1.4 miles (local spend)</Feature><Feature>$1 = 2.4 miles (overseas spend)</Feature><Feature>Earn 3 miles every S$1 spent on Singapore Airlines, SilkAir &amp; KrisShop</Feature><Feature>Bonus 20,000 miles with spend of $50,000 in a year</Feature><Feature>Personal accident and travel inconvenience insurance coverage of up to S$1,000,000</Feature><Feature>Rebate of S$45 for each one-way limousine service to Singapore Changi Airport with min. overseas spend of S$1,000 within each qualifying quarter</Feature></Details>
  
  <Details Name="sc_airmiles_rating">
  <Feature>5</Feature></Details>

  <Details Name="sc_cashback_details">
  </Details>
  
  <Details Name="sc_cashback_rating">
  </Details>

  <Details Name="sc_dining_details">
  </Details>
  
  <Details Name="sc_dining_rating">
  </Details>

  <Details Name="sc_entertainment_details">
  </Details>
  
  <Details Name="sc_entertainment_rating">
  </Details>

  <Details Name="sc_grocery_details">
  </Details>
  
  <Details Name="sc_grocery_rating">
  </Details>

  <Details Name="sc_petrol_details">
  </Details>
  
  <Details Name="sc_petrol_rating">    
  </Details>

  <Details Name="sc_rewards_details">
  </Details>
  
  <Details Name="sc_rewards_rating">   
  </Details>

  <Details Name="sc_shopping_details">
  </Details>
  
  <Details Name="sc_shopping_rating">
  </Details>

  <Details Name="sc_student_details">
  </Details>
  
  <Details Name="sc_student_rating">
  </Details>

  <Details Name="sc_main_image">
  <Feature>./images/UOB Prvi Miles Platinum American Express Card.png</Feature></Details>

</CreaditDetails>